MANIFEST.in
l10n_in_private_chart.xml
l10n_in_private_tax_template.xml
l10n_in_public_chart.xml
l10n_in_public_tax_template.xml
l10n_in_tax_code_template.xml
l10n_in_wizard.xml
setup.py
./__init__.py
./__openerp__.py
i18n/ar.po
i18n/br.po
i18n/ca.po
i18n/da.po
i18n/de.po
i18n/es.po
i18n/es_CR.po
i18n/es_MX.po
i18n/es_PY.po
i18n/es_VE.po
i18n/et.po
i18n/fr.po
i18n/gl.po
i18n/hu.po
i18n/it.po
i18n/l10n_in.pot
i18n/nl.po
i18n/oc.po
i18n/pt.po
i18n/pt_BR.po
i18n/ru.po
i18n/sl.po
i18n/sr@latin.po
i18n/sv.po
i18n/tr.po
images/config_chart_l10n_in.jpeg
images/l10n_in_chart.jpeg
openerp_l10n_in.egg-info/PKG-INFO
openerp_l10n_in.egg-info/SOURCES.txt
openerp_l10n_in.egg-info/dependency_links.txt
openerp_l10n_in.egg-info/requires.txt
openerp_l10n_in.egg-info/top_level.txt
static/src/img/icon.png